ssdk_alpha_ti/__init__.py
ssdk_alpha_ti/api_client.py
ssdk_alpha_ti/api_response.py
ssdk_alpha_ti/configuration.py
ssdk_alpha_ti/exceptions.py
ssdk_alpha_ti/py.typed
ssdk_alpha_ti/rest.py
ssdk_alpha_ti/api/__init__.py
ssdk_alpha_ti/api/brand_api.py
ssdk_alpha_ti/api/default_api.py
ssdk_alpha_ti/api/generation_api.py
ssdk_alpha_ti/api/healthcheck_api.py
ssdk_alpha_ti/api/prompt_api.py
ssdk_alpha_ti/api/source_api.py
ssdk_alpha_ti/api/swagger_api.py
ssdk_alpha_ti/api/swaggers_api.py
ssdk_alpha_ti/api/tenant_api.py
ssdk_alpha_ti/api/worker_api.py
ssdk_alpha_ti/models/__init__.py
ssdk_alpha_ti/models/brand_compass_progress_schema.py
ssdk_alpha_ti/models/brand_compass_response_schema.py
ssdk_alpha_ti/models/brand_create_schema.py
ssdk_alpha_ti/models/brand_response_schema.py
ssdk_alpha_ti/models/brand_update_schema.py
ssdk_alpha_ti/models/generation_create_schema.py
ssdk_alpha_ti/models/generation_response_schema.py
ssdk_alpha_ti/models/prompt_create_schema.py
ssdk_alpha_ti/models/prompt_response_schema.py
ssdk_alpha_ti/models/prompt_update_schema.py
ssdk_alpha_ti/models/source_response_schema.py
ssdk_alpha_ti/models/tenant_create_schema.py
ssdk_alpha_ti/models/tenant_response_schema.py
ssdk_alpha_ti/models/tenant_settings_schema.py
ssdk_alpha_ti/models/tenant_update_schema.py
ssdk_alpha_ti/models/worker_create_schema.py
ssdk_alpha_ti/models/worker_response_schema.py
ssdk_alpha_ti/models/worker_update_schema.py
ssdk_alpha_ti-0.0.2.dist-info/METADATA
ssdk_alpha_ti-0.0.2.dist-info/WHEEL
ssdk_alpha_ti-0.0.2.dist-info/top_level.txt
ssdk_alpha_ti-0.0.2.dist-info/RECORD
